CHANGELOG.md
neptune_tensorboard/__init__.py
neptune_tensorboard/integration/__init__.py
neptune_tensorboard/integration/pytorch_integration.py
neptune_tensorboard/integration/tensorboardx_integration.py
neptune_tensorboard/integration/tensorflow_integration.py
neptune_tensorboard/integration/utils.py
neptune_tensorboard/integration/version.py
neptune_tensorboard/sync/__init__.py
neptune_tensorboard/sync/sync_impl.py
neptune_tensorboard_plugin/__init__.py
neptune_tensorboard-1.0.3.dist-info/LICENSE
neptune_tensorboard-1.0.3.dist-info/METADATA
neptune_tensorboard-1.0.3.dist-info/WHEEL
neptune_tensorboard-1.0.3.dist-info/entry_points.txt
neptune_tensorboard-1.0.3.dist-info/RECORD
